[{"chp": "01", "firstvs": "01"}, {"chp": "01", "firstvs": "04"}, {"chp": "01", "firstvs": "06"}, {"chp": "01", "firstvs": "09"}, {"chp": "01", "firstvs": "13"}, {"chp": "01", "firstvs": "16"}, {"chp": "01", "firstvs": "18"}, {"chp": "01", "firstvs": "20"}, {"chp": "02", "firstvs": "01"}, {"chp": "02", "firstvs": "03"}, {"chp": "02", "firstvs": "04"}, {"chp": "02", "firstvs": "07"}, {"chp": "02", "firstvs": "09"}, {"chp": "02", "firstvs": "11"}, {"chp": "02", "firstvs": "12"}, {"chp": "03", "firstvs": "01"}, {"chp": "03", "firstvs": "04"}, {"chp": "03", "firstvs": "06"}, {"chp": "03", "firstvs": "08"}, {"chp": "03", "firstvs": "11"}, {"chp": "03", "firstvs": "13"}, {"chp": "03", "firstvs": "15"}, {"chp": "03", "firstvs": "17"}, {"chp": "03", "firstvs": "20"}, {"chp": "03", "firstvs": "23"}, {"chp": "03", "firstvs": "25"}, {"chp": "04", "firstvs": "01"}, {"chp": "04", "firstvs": "04"}, {"chp": "04", "firstvs": "07"}, {"chp": "04", "firstvs": "10"}, {"chp": "04", "firstvs": "12"}, {"chp": "04", "firstvs": "14"}, {"chp": "04", "firstvs": "16"}, {"chp": "04", "firstvs": "18"}, {"chp": "04", "firstvs": "20"}, {"chp": "05", "firstvs": "01"}, {"chp": "05", "firstvs": "04"}, {"chp": "05", "firstvs": "06"}, {"chp": "05", "firstvs": "08"}, {"chp": "05", "firstvs": "11"}, {"chp": "05", "firstvs": "14"}, {"chp": "05", "firstvs": "17"}, {"chp": "05", "firstvs": "20"}, {"chp": "05", "firstvs": "23"}, {"chp": "05", "firstvs": "26"}, {"chp": "06", "firstvs": "01"}, {"chp": "06", "firstvs": "04"}, {"chp": "06", "firstvs": "07"}, {"chp": "06", "firstvs": "10"}, {"chp": "06", "firstvs": "12"}, {"chp": "06", "firstvs": "14"}, {"chp": "06", "firstvs": "18"}, {"chp": "06", "firstvs": "21"}, {"chp": "06", "firstvs": "24"}, {"chp": "06", "firstvs": "26"}, {"chp": "06", "firstvs": "28"}, {"chp": "07", "firstvs": "01"}, {"chp": "07", "firstvs": "04"}, {"chp": "07", "firstvs": "06"}, {"chp": "07", "firstvs": "08"}, {"chp": "07", "firstvs": "11"}, {"chp": "07", "firstvs": "13"}, {"chp": "07", "firstvs": "16"}, {"chp": "07", "firstvs": "19"}, {"chp": "07", "firstvs": "21"}, {"chp": "08", "firstvs": "01"}, {"chp": "08", "firstvs": "04"}, {"chp": "08", "firstvs": "06"}, {"chp": "08", "firstvs": "08"}, {"chp": "08", "firstvs": "11"}, {"chp": "08", "firstvs": "13"}, {"chp": "08", "firstvs": "16"}, {"chp": "08", "firstvs": "19"}, {"chp": "08", "firstvs": "21"}, {"chp": "09", "firstvs": "01"}, {"chp": "09", "firstvs": "04"}, {"chp": "09", "firstvs": "07"}, {"chp": "09", "firstvs": "10"}, {"chp": "09", "firstvs": "13"}, {"chp": "09", "firstvs": "16"}, {"chp": "09", "firstvs": "19"}, {"chp": "09", "firstvs": "21"}, {"chp": "09", "firstvs": "25"}, {"chp": "09", "firstvs": "27"}, {"chp": "09", "firstvs": "30"}, {"chp": "09", "firstvs": "32"}, {"chp": "09", "firstvs": "34"}, {"chp": "10", "firstvs": "01"}, {"chp": "10", "firstvs": "04"}, {"chp": "10", "firstvs": "08"}, {"chp": "10", "firstvs": "10"}, {"chp": "10", "firstvs": "12"}, {"chp": "10", "firstvs": "15"}, {"chp": "10", "firstvs": "17"}, {"chp": "10", "firstvs": "18"}, {"chp": "10", "firstvs": "20"}, {"chp": "11", "firstvs": "01"}, {"chp": "11", "firstvs": "04"}, {"chp": "11", "firstvs": "07"}, {"chp": "11", "firstvs": "10"}, {"chp": "11", "firstvs": "13"}, {"chp": "11", "firstvs": "15"}, {"chp": "11", "firstvs": "18"}, {"chp": "11", "firstvs": "20"}, {"chp": "12", "firstvs": "01"}, {"chp": "12", "firstvs": "04"}, {"chp": "12", "firstvs": "07"}, {"chp": "12", "firstvs": "09"}, {"chp": "12", "firstvs": "11"}, {"chp": "12", "firstvs": "13"}, {"chp": "12", "firstvs": "16"}, {"chp": "12", "firstvs": "19"}, {"chp": "12", "firstvs": "22"}, {"chp": "12", "firstvs": "24"}, {"chp": "13", "firstvs": "01"}, {"chp": "13", "firstvs": "03"}, {"chp": "13", "firstvs": "06"}, {"chp": "13", "firstvs": "09"}, {"chp": "13", "firstvs": "11"}, {"chp": "13", "firstvs": "13"}, {"chp": "13", "firstvs": "16"}, {"chp": "13", "firstvs": "18"}, {"chp": "13", "firstvs": "20"}, {"chp": "13", "firstvs": "23"}, {"chp": "13", "firstvs": "26"}, {"chp": "14", "firstvs": "01"}, {"chp": "14", "firstvs": "04"}, {"chp": "14", "firstvs": "07"}, {"chp": "14", "firstvs": "10"}, {"chp": "14", "firstvs": "13"}, {"chp": "14", "firstvs": "15"}, {"chp": "14", "firstvs": "18"}, {"chp": "14", "firstvs": "20"}, {"chp": "15", "firstvs": "01"}, {"chp": "15", "firstvs": "04"}, {"chp": "15", "firstvs": "07"}, {"chp": "15", "firstvs": "10"}, {"chp": "15", "firstvs": "12"}, {"chp": "15", "firstvs": "15"}, {"chp": "15", "firstvs": "17"}, {"chp": "15", "firstvs": "19"}, {"chp": "15", "firstvs": "22"}, {"chp": "15", "firstvs": "25"}, {"chp": "15", "firstvs": "27"}, {"chp": "15", "firstvs": "29"}, {"chp": "15", "firstvs": "31"}, {"chp": "15", "firstvs": "34"}, {"chp": "16", "firstvs": "01"}, {"chp": "16", "firstvs": "04"}, {"chp": "16", "firstvs": "06"}, {"chp": "16", "firstvs": "09"}, {"chp": "16", "firstvs": "11"}, {"chp": "16", "firstvs": "13"}, {"chp": "16", "firstvs": "15"}, {"chp": "16", "firstvs": "18"}, {"chp": "16", "firstvs": "20"}, {"chp": "17", "firstvs": "01"}, {"chp": "17", "firstvs": "04"}, {"chp": "17", "firstvs": "06"}, {"chp": "17", "firstvs": "09"}, {"chp": "17", "firstvs": "11"}, {"chp": "17", "firstvs": "13"}, {"chp": "18", "firstvs": "01"}, {"chp": "18", "firstvs": "03"}, {"chp": "18", "firstvs": "05"}, {"chp": "18", "firstvs": "07"}, {"chp": "18", "firstvs": "09"}, {"chp": "18", "firstvs": "12"}, {"chp": "18", "firstvs": "14"}, {"chp": "18", "firstvs": "16"}, {"chp": "18", "firstvs": "18"}, {"chp": "18", "firstvs": "21"}, {"chp": "19", "firstvs": "01"}, {"chp": "19", "firstvs": "03"}, {"chp": "19", "firstvs": "05"}, {"chp": "19", "firstvs": "07"}, {"chp": "19", "firstvs": "10"}, {"chp": "19", "firstvs": "13"}, {"chp": "19", "firstvs": "15"}, {"chp": "19", "firstvs": "17"}, {"chp": "19", "firstvs": "20"}, {"chp": "19", "firstvs": "23"}, {"chp": "19", "firstvs": "25"}, {"chp": "19", "firstvs": "28"}, {"chp": "20", "firstvs": "01"}, {"chp": "20", "firstvs": "04"}, {"chp": "20", "firstvs": "06"}, {"chp": "20", "firstvs": "08"}, {"chp": "20", "firstvs": "10"}, {"chp": "20", "firstvs": "12"}, {"chp": "20", "firstvs": "15"}, {"chp": "20", "firstvs": "17"}, {"chp": "20", "firstvs": "20"}, {"chp": "20", "firstvs": "23"}, {"chp": "20", "firstvs": "26"}, {"chp": "20", "firstvs": "28"}, {"chp": "21", "firstvs": "01"}, {"chp": "21", "firstvs": "04"}, {"chp": "21", "firstvs": "07"}, {"chp": "21", "firstvs": "10"}, {"chp": "21", "firstvs": "13"}, {"chp": "21", "firstvs": "16"}, {"chp": "21", "firstvs": "19"}, {"chp": "21", "firstvs": "22"}, {"chp": "21", "firstvs": "25"}, {"chp": "21", "firstvs": "27"}, {"chp": "21", "firstvs": "29"}, {"chp": "21", "firstvs": "31"}, {"chp": "21", "firstvs": "34"}, {"chp": "22", "firstvs": "01"}, {"chp": "22", "firstvs": "04"}, {"chp": "22", "firstvs": "06"}, {"chp": "22", "firstvs": "09"}, {"chp": "22", "firstvs": "12"}, {"chp": "22", "firstvs": "15"}, {"chp": "22", "firstvs": "18"}, {"chp": "22", "firstvs": "21"}, {"chp": "22", "firstvs": "23"}, {"chp": "22", "firstvs": "26"}, {"chp": "22", "firstvs": "29"}, {"chp": "23", "firstvs": "01"}, {"chp": "23", "firstvs": "03"}, {"chp": "23", "firstvs": "06"}, {"chp": "23", "firstvs": "08"}, {"chp": "23", "firstvs": "10"}, {"chp": "23", "firstvs": "13"}, {"chp": "23", "firstvs": "15"}, {"chp": "24", "firstvs": "01"}, {"chp": "24", "firstvs": "02"}, {"chp": "24", "firstvs": "05"}, {"chp": "24", "firstvs": "08"}, {"chp": "24", "firstvs": "11"}, {"chp": "24", "firstvs": "13"}, {"chp": "24", "firstvs": "15"}, {"chp": "24", "firstvs": "18"}, {"chp": "24", "firstvs": "20"}, {"chp": "24", "firstvs": "22"}, {"chp": "24", "firstvs": "24"}, {"chp": "25", "firstvs": "01"}, {"chp": "25", "firstvs": "04"}, {"chp": "26", "firstvs": "01"}, {"chp": "26", "firstvs": "05"}, {"chp": "26", "firstvs": "07"}, {"chp": "26", "firstvs": "09"}, {"chp": "26", "firstvs": "11"}, {"chp": "26", "firstvs": "13"}, {"chp": "27", "firstvs": "01"}, {"chp": "27", "firstvs": "04"}, {"chp": "27", "firstvs": "06"}, {"chp": "27", "firstvs": "08"}, {"chp": "27", "firstvs": "11"}, {"chp": "27", "firstvs": "13"}, {"chp": "27", "firstvs": "15"}, {"chp": "27", "firstvs": "18"}, {"chp": "27", "firstvs": "20"}, {"chp": "27", "firstvs": "22"}, {"chp": "28", "firstvs": "01"}, {"chp": "28", "firstvs": "03"}, {"chp": "28", "firstvs": "05"}, {"chp": "28", "firstvs": "07"}, {"chp": "28", "firstvs": "09"}, {"chp": "28", "firstvs": "12"}, {"chp": "28", "firstvs": "15"}, {"chp": "28", "firstvs": "18"}, {"chp": "28", "firstvs": "20"}, {"chp": "28", "firstvs": "23"}, {"chp": "28", "firstvs": "26"}, {"chp": "29", "firstvs": "01"}, {"chp": "29", "firstvs": "04"}, {"chp": "29", "firstvs": "07"}, {"chp": "29", "firstvs": "09"}, {"chp": "29", "firstvs": "11"}, {"chp": "29", "firstvs": "14"}, {"chp": "29", "firstvs": "17"}, {"chp": "29", "firstvs": "20"}, {"chp": "29", "firstvs": "23"}, {"chp": "29", "firstvs": "25"}, {"chp": "30", "firstvs": "01"}, {"chp": "30", "firstvs": "04"}, {"chp": "30", "firstvs": "07"}, {"chp": "30", "firstvs": "09"}, {"chp": "30", "firstvs": "12"}, {"chp": "30", "firstvs": "14"}, {"chp": "30", "firstvs": "16"}, {"chp": "30", "firstvs": "18"}, {"chp": "30", "firstvs": "20"}, {"chp": "30", "firstvs": "22"}, {"chp": "30", "firstvs": "24"}, {"chp": "30", "firstvs": "27"}, {"chp": "30", "firstvs": "30"}, {"chp": "31", "firstvs": "01"}, {"chp": "31", "firstvs": "03"}, {"chp": "31", "firstvs": "05"}, {"chp": "31", "firstvs": "07"}, {"chp": "31", "firstvs": "09"}, {"chp": "31", "firstvs": "11"}, {"chp": "31", "firstvs": "13"}, {"chp": "31", "firstvs": "16"}, {"chp": "31", "firstvs": "19"}, {"chp": "31", "firstvs": "22"}, {"chp": "31", "firstvs": "24"}, {"chp": "31", "firstvs": "26"}, {"chp": "31", "firstvs": "29"}, {"chp": "31", "firstvs": "31"}, {"chp": "31", "firstvs": "33"}, {"chp": "31", "firstvs": "35"}, {"chp": "31", "firstvs": "38"}, {"chp": "32", "firstvs": "01"}, {"chp": "32", "firstvs": "03"}, {"chp": "32", "firstvs": "06"}, {"chp": "32", "firstvs": "08"}, {"chp": "32", "firstvs": "11"}, {"chp": "32", "firstvs": "13"}, {"chp": "32", "firstvs": "15"}, {"chp": "32", "firstvs": "17"}, {"chp": "32", "firstvs": "20"}, {"chp": "33", "firstvs": "01"}, {"chp": "33", "firstvs": "04"}, {"chp": "33", "firstvs": "06"}, {"chp": "33", "firstvs": "08"}, {"chp": "33", "firstvs": "10"}, {"chp": "33", "firstvs": "13"}, {"chp": "33", "firstvs": "16"}, {"chp": "33", "firstvs": "19"}, {"chp": "33", "firstvs": "21"}, {"chp": "33", "firstvs": "23"}, {"chp": "33", "firstvs": "25"}, {"chp": "33", "firstvs": "27"}, {"chp": "33", "firstvs": "29"}, {"chp": "33", "firstvs": "31"}, {"chp": "34", "firstvs": "01"}, {"chp": "34", "firstvs": "04"}, {"chp": "34", "firstvs": "07"}, {"chp": "34", "firstvs": "10"}, {"chp": "34", "firstvs": "13"}, {"chp": "34", "firstvs": "16"}, {"chp": "34", "firstvs": "18"}, {"chp": "34", "firstvs": "21"}, {"chp": "34", "firstvs": "24"}, {"chp": "34", "firstvs": "26"}, {"chp": "34", "firstvs": "29"}, {"chp": "34", "firstvs": "31"}, {"chp": "34", "firstvs": "34"}, {"chp": "34", "firstvs": "36"}, {"chp": "35", "firstvs": "01"}, {"chp": "35", "firstvs": "04"}, {"chp": "35", "firstvs": "06"}, {"chp": "35", "firstvs": "09"}, {"chp": "35", "firstvs": "12"}, {"chp": "35", "firstvs": "15"}, {"chp": "36", "firstvs": "01"}, {"chp": "36", "firstvs": "04"}, {"chp": "36", "firstvs": "06"}, {"chp": "36", "firstvs": "08"}, {"chp": "36", "firstvs": "10"}, {"chp": "36", "firstvs": "13"}, {"chp": "36", "firstvs": "15"}, {"chp": "36", "firstvs": "17"}, {"chp": "36", "firstvs": "19"}, {"chp": "36", "firstvs": "22"}, {"chp": "36", "firstvs": "25"}, {"chp": "36", "firstvs": "27"}, {"chp": "36", "firstvs": "30"}, {"chp": "36", "firstvs": "32"}, {"chp": "37", "firstvs": "01"}, {"chp": "37", "firstvs": "04"}, {"chp": "37", "firstvs": "07"}, {"chp": "37", "firstvs": "10"}, {"chp": "37", "firstvs": "12"}, {"chp": "37", "firstvs": "14"}, {"chp": "37", "firstvs": "16"}, {"chp": "37", "firstvs": "18"}, {"chp": "37", "firstvs": "21"}, {"chp": "37", "firstvs": "23"}, {"chp": "38", "firstvs": "01"}, {"chp": "38", "firstvs": "04"}, {"chp": "38", "firstvs": "06"}, {"chp": "38", "firstvs": "08"}, {"chp": "38", "firstvs": "10"}, {"chp": "38", "firstvs": "12"}, {"chp": "38", "firstvs": "14"}, {"chp": "38", "firstvs": "16"}, {"chp": "38", "firstvs": "19"}, {"chp": "38", "firstvs": "22"}, {"chp": "38", "firstvs": "25"}, {"chp": "38", "firstvs": "28"}, {"chp": "38", "firstvs": "31"}, {"chp": "38", "firstvs": "34"}, {"chp": "38", "firstvs": "36"}, {"chp": "38", "firstvs": "39"}, {"chp": "38", "firstvs": "41"}, {"chp": "39", "firstvs": "01"}, {"chp": "39", "firstvs": "03"}, {"chp": "39", "firstvs": "05"}, {"chp": "39", "firstvs": "07"}, {"chp": "39", "firstvs": "09"}, {"chp": "39", "firstvs": "11"}, {"chp": "39", "firstvs": "13"}, {"chp": "39", "firstvs": "16"}, {"chp": "39", "firstvs": "19"}, {"chp": "39", "firstvs": "21"}, {"chp": "39", "firstvs": "24"}, {"chp": "39", "firstvs": "26"}, {"chp": "39", "firstvs": "27"}, {"chp": "39", "firstvs": "29"}, {"chp": "40", "firstvs": "01"}, {"chp": "40", "firstvs": "03"}, {"chp": "40", "firstvs": "06"}, {"chp": "40", "firstvs": "08"}, {"chp": "40", "firstvs": "10"}, {"chp": "40", "firstvs": "12"}, {"chp": "40", "firstvs": "15"}, {"chp": "40", "firstvs": "17"}, {"chp": "40", "firstvs": "19"}, {"chp": "40", "firstvs": "22"}, {"chp": "41", "firstvs": "01"}, {"chp": "41", "firstvs": "04"}, {"chp": "41", "firstvs": "07"}, {"chp": "41", "firstvs": "10"}, {"chp": "41", "firstvs": "13"}, {"chp": "41", "firstvs": "16"}, {"chp": "41", "firstvs": "19"}, {"chp": "41", "firstvs": "22"}, {"chp": "41", "firstvs": "25"}, {"chp": "41", "firstvs": "28"}, {"chp": "41", "firstvs": "31"}, {"chp": "41", "firstvs": "33"}, {"chp": "42", "firstvs": "01"}, {"chp": "42", "firstvs": "04"}, {"chp": "42", "firstvs": "07"}, {"chp": "42", "firstvs": "10"}, {"chp": "42", "firstvs": "12"}, {"chp": "42", "firstvs": "15"}]