[{"chp": "01", "firstvs": "01"}, {"chp": "01", "firstvs": "03"}, {"chp": "01", "firstvs": "05"}, {"chp": "01", "firstvs": "08"}, {"chp": "01", "firstvs": "10"}, {"chp": "01", "firstvs": "12"}, {"chp": "01", "firstvs": "13"}, {"chp": "01", "firstvs": "15"}, {"chp": "02", "firstvs": "01"}, {"chp": "02", "firstvs": "02"}, {"chp": "02", "firstvs": "04"}, {"chp": "02", "firstvs": "06"}, {"chp": "02", "firstvs": "09"}, {"chp": "02", "firstvs": "12"}, {"chp": "02", "firstvs": "15"}, {"chp": "02", "firstvs": "17"}, {"chp": "02", "firstvs": "18"}, {"chp": "03", "firstvs": "01"}, {"chp": "03", "firstvs": "03"}, {"chp": "03", "firstvs": "04"}, {"chp": "03", "firstvs": "06"}, {"chp": "03", "firstvs": "07"}, {"chp": "03", "firstvs": "09"}, {"chp": "03", "firstvs": "11"}, {"chp": "03", "firstvs": "13"}, {"chp": "03", "firstvs": "14"}, {"chp": "03", "firstvs": "16"}, {"chp": "03", "firstvs": "17"}, {"chp": "03", "firstvs": "18"}]