[{"id": "01", "tn": [{"ref": "Mount Nebo", "text": "This is the highest point of Mount Pisgah which is in the northern part of the Abarim mountain range. Translate as in [[:en:bible:notes:deu:32:48|32:49]]."}, {"ref": "Pisgah", "text": "Translate as in [[:en:bible:notes:deu:03:17|3:17]]."}, {"ref": "the City of Palms", "text": "This is another name for Jericho. (See: [[:en:ta:vol1:translate:translate_names]])"}]}, {"id": "04", "tn": [{"ref": "Beth Peor", "text": "This was a town in Moab. See how you translated this in [[:en:bible:notes:deu:03:28|3:29]]."}, {"ref": "look at it with your eyes", "text": "\"see it for yourself\""}, {"ref": "to this day", "text": "This refers to the time that this was written or edited, not to the present time in the twenty-first century."}]}, {"id": "07", "tn": [{"ref": "one hundred twenty years old ... thirty days", "text": "\"120 years old ... 30 days\" (See: [[:en:ta:vol2:translate:translate_numbers]])"}, {"ref": "his eye was not dim, nor his natural force abated", "text": "This means his eyes and body were still strong and healthy."}]}, {"id": "09", "tn": [{"ref": "son of Nun", "text": "Translate as in [[:en:bible:notes:deu:01:37|1:38]]."}, {"ref": "Joshua ... was full of the spirit of wisdom", "text": "The writer speaks as if Joshua were a container and the spirit were a physical object that could be put into a container. AT: \"Yahweh enabled Joshua ... to be very wise\" (See: [[:en:ta:vol1:translate:figs_metaphor]])"}, {"ref": "Moses had laid his hands on him", "text": "The full meaning of this statement can be made clear. AT: \"Moses had laid his hands on him to set Joshua apart so Joshua would serve Yahweh.\" (See: [[:en:ta:vol1:translate:figs_explicit]])"}]}, {"id": "10", "tn": [{"ref": "Yahweh knew face to face", "text": "This is an idiom. It means Yahweh and Moses had a very close relationship. (See: [[:en:ta:vol1:translate:figs_idiom]])"}, {"ref": "in all the great", "text": "\"who did all the great\""}]}]